cozepy/__init__.py
cozepy/api_apps/__init__.py
cozepy/api_apps/events/__init__.py
cozepy/apps/__init__.py
cozepy/audio/__init__.py
cozepy/audio/live/__init__.py
cozepy/audio/rooms/__init__.py
cozepy/audio/speech/__init__.py
cozepy/audio/transcriptions/__init__.py
cozepy/audio/voiceprint_groups/__init__.py
cozepy/audio/voiceprint_groups/features/__init__.py
cozepy/audio/voices/__init__.py
cozepy/auth/__init__.py
cozepy/bots/__init__.py
cozepy/chat/__init__.py
cozepy/chat/message/__init__.py
cozepy/config.py
cozepy/conversations/__init__.py
cozepy/conversations/message/__init__.py
cozepy/conversations/message/feedback/__init__.py
cozepy/coze.py
cozepy/datasets/__init__.py
cozepy/datasets/documents/__init__.py
cozepy/datasets/images/__init__.py
cozepy/enterprises/__init__.py
cozepy/enterprises/members/__init__.py
cozepy/exception.py
cozepy/files/__init__.py
cozepy/folders/__init__.py
cozepy/knowledge/__init__.py
cozepy/knowledge/documents/__init__.py
cozepy/log.py
cozepy/model.py
cozepy/py.typed
cozepy/request.py
cozepy/templates/__init__.py
cozepy/users/__init__.py
cozepy/util.py
cozepy/variables/__init__.py
cozepy/version.py
cozepy/websockets/__init__.py
cozepy/websockets/audio/__init__.py
cozepy/websockets/audio/speech/__init__.py
cozepy/websockets/audio/transcriptions/__init__.py
cozepy/websockets/chat/__init__.py
cozepy/websockets/ws.py
cozepy/workflows/__init__.py
cozepy/workflows/chat/__init__.py
cozepy/workflows/runs/__init__.py
cozepy/workflows/runs/run_histories/__init__.py
cozepy/workflows/runs/run_histories/execute_nodes/__init__.py
cozepy/workspaces/__init__.py
cozepy/workspaces/members/__init__.py
cozepy-0.19.0.dist-info/LICENSE
cozepy-0.19.0.dist-info/METADATA
cozepy-0.19.0.dist-info/WHEEL
cozepy-0.19.0.dist-info/RECORD
